{
  "main": {
    "id": "3fb92f0e43726f2c",
    "type": "split",
    "children": [
      {
        "id": "3b05c4b245fdda90",
        "type": "tabs",
        "children": [
          {
            "id": "af99fc1f4a6460c2",
            "type": "leaf",
            "state": {
              "type": "markdown",
              "state": {
                "file": "Cohort/Module 1/1.10 Strings/Notes.md",
                "mode": "source",
                "source": false
              },
              "icon": "lucide-file",
              "title": "Notes"
            }
          }
        ]
      }
    ],
    "direction": "vertical"
  },
  "left": {
    "id": "7c8235dc591c784d",
    "type": "split",
    "children": [
      {
        "id": "d0760b9dc6776a3c",
        "type": "tabs",
        "children": [
          {
            "id": "ce01d6c1c449340f",
            "type": "leaf",
            "state": {
              "type": "file-explorer",
              "state": {
                "sortOrder": "alphabetical",
                "autoReveal": false
              },
              "icon": "lucide-folder-closed",
              "title": "Files"
            }
          },
          {
            "id": "c7539f1fbaa5e4ea",
            "type": "leaf",
            "state": {
              "type": "search",
              "state": {
                "query": "",
                "matchingCase": false,
                "explainSearch": false,
                "collapseAll": false,
                "extraContext": false,
                "sortOrder": "alphabetical"
              },
              "icon": "lucide-search",
              "title": "Search"
            }
          },
          {
            "id": "3da080f71a20d852",
            "type": "leaf",
            "state": {
              "type": "bookmarks",
              "state": {},
              "icon": "lucide-bookmark",
              "title": "Bookmarks"
            }
          }
        ]
      }
    ],
    "direction": "horizontal",
    "width": 438.51103591918945
  },
  "right": {
    "id": "ef1c67bb5b04dc0e",
    "type": "split",
    "children": [
      {
        "id": "e212ebace3e00c38",
        "type": "tabs",
        "children": [
          {
            "id": "7ae2cfd60dda9913",
            "type": "leaf",
            "state": {
              "type": "backlink",
              "state": {
                "file": "Cohort/Intermediate DSA-Introduction to Problem Solving.md",
                "collapseAll": false,
                "extraContext": false,
                "sortOrder": "alphabetical",
                "showSearch": false,
                "searchQuery": "",
                "backlinkCollapsed": false,
                "unlinkedCollapsed": true
              },
              "icon": "links-coming-in",
              "title": "Backlinks for Intermediate DSA-Introduction to Problem Solving"
            }
          },
          {
            "id": "293e69ca92fca48e",
            "type": "leaf",
            "state": {
              "type": "outgoing-link",
              "state": {
                "file": "Azure/Durable Functions/YT/5. Replay Behavior.md",
                "linksCollapsed": false,
                "unlinkedCollapsed": true
              },
              "icon": "links-going-out",
              "title": "Outgoing links from 5. Replay Behavior"
            }
          },
          {
            "id": "350a01964239df65",
            "type": "leaf",
            "state": {
              "type": "tag",
              "state": {
                "sortOrder": "frequency",
                "useHierarchy": true
              },
              "icon": "lucide-tags",
              "title": "Tags"
            }
          },
          {
            "id": "35df9227e52b3677",
            "type": "leaf",
            "state": {
              "type": "outline",
              "state": {
                "file": "Azure/Durable Functions/YT/5. Replay Behavior.md"
              },
              "icon": "lucide-list",
              "title": "Outline of 5. Replay Behavior"
            }
          }
        ]
      }
    ],
    "direction": "horizontal",
    "width": 200,
    "collapsed": true
  },
  "left-ribbon": {
    "hiddenItems": {
      "switcher:Open quick switcher": false,
      "graph:Open graph view": false,
      "canvas:Create new canvas": false,
      "daily-notes:Open today's daily note": false,
      "templates:Insert template": false,
      "command-palette:Open command palette": false,
      "github-sync:Sync with Remote": false
    }
  },
  "active": "af99fc1f4a6460c2",
  "lastOpenFiles": [
    "Cohort/Module 1/0.8 Bit_Manipulation_Basics/Intermediate_DSA___Bit_Manipulation_Basics_2.pdf",
    "Cohort/Module 1/0.8 Bit_Manipulation_Basics/Scaler Companion.pdf",
    "Cohort/Module 1/1.10 Strings/Notes.md",
    "Cohort/Module 1/1.10 Strings/s2.png",
    "Cohort/Module 1/1.10 Strings/s1.png",
    "Cohort/Module 1/0.9 Tow D Matrices/Notes.md",
    "Cohort/Module 1/1.10 Strings",
    "SQL Questions/LeetCode/3. Basic Aggregate Functions/Questions.md",
    "Cohort/Module 1/0.7 Lab Session on Memory Management & Sorting Basics/Notes.md",
    "Cohort Prac/PrefixSum/Easy.md",
    "Cohort/Module 1/0.9 Tow D Matrices",
    "Cohort Prac/Longest Subarray with Sum K.md",
    "Cohort Prac/Count Subarrays Whose Sum Equals K.md",
    "Cohort/Module 1/0.6 Sliding Window & Contribution Technique/Questions.md",
    "Cohort/Module 1/0.5 Prefix_Sum___Carry_Forward.pdf",
    "Cohort/Module 1/Questions.md",
    "Microservices/brew-aspnetcore-microservices/Content/Validation-middleware.png",
    "Cohort Prac/PrefixSum",
    "Cohort Prac",
    "Microservices/brew-aspnetcore-microservices/Content/rest-api-and-cross-cutting-concerns.png",
    "Microservices/brew-aspnetcore-microservices/Content/MediatR-pipeline-behavior.png",
    "Microservices/brew-aspnetcore-microservices/Content/Logging-middleware.png",
    "Microservices/brew-aspnetcore-microservices/Content/Developing-catalog-api.png",
    "Microservices/brew-aspnetcore-microservices/Content/Deployment-strategy.png",
    "Microservices/brew-aspnetcore-microservices/Content/Cqrs-mediatr-request-lifecycle.png",
    "Microservices/brew-aspnetcore-microservices/Content/Big-picture-course-project.png",
    "Microservices/brew-aspnetcore-microservices/Decomposition-of-e-commerce-ms.pdf",
    "Microservices/brew-aspnetcore-microservices/What's-new-in-dotnet8-and-C#-12-features.pdf",
    "Cohort/Module 1/0.8 Bit_Manipulation_Basics",
    "Dev/YouTube/LeetCode’s Top 50 questions.md",
    "Dev/Udemy/Courses.md",
    "J/Issues.md",
    "Dev/YouTube/ConfigDemo.md",
    "Dev/Redis Cache.md",
    "Dev/Primitive Obsession.md",
    "Dev/Keyed Services.md",
    "Dev/gRPC.md",
    "Dev/Dependency Injection.md",
    "Dev/YouTube/WebSocket.md",
    "Dev/YouTube/Redis Script for Video Upload.md",
    "DSA/Array/Questions.md",
    "Cohort/Module 1/0.0 Intermediate DSA-Introduction to Problem Solving.md",
    "J/Madan Reddy/Spring Boot/Notebook.md",
    "J/DI.md",
    "J/Madan Reddy/Spring Boot/Books/Create a Bean.md"
  ]
}